wsgiappversion/__init__.py
wsgiappversion/base.py
wsgiappversion-1.0.0.dist-info/DESCRIPTION.rst
wsgiappversion-1.0.0.dist-info/METADATA
wsgiappversion-1.0.0.dist-info/metadata.json
wsgiappversion-1.0.0.dist-info/RECORD
wsgiappversion-1.0.0.dist-info/top_level.txt
wsgiappversion-1.0.0.dist-info/WHEEL
