Metadata-Version: 2.0
Name: wsgiappversion
Version: 1.0.0
Summary: Wsgi middleware that exposes an app's version number
Home-page: https://github.com/LostProperty/wsgiappversion
Author: Rob Berry
Author-email: rob@lostpropertyhq.com
License: MIT
Keywords: wsgi version
Platform: UNKNOWN
Classifier: Intended Audience :: Developers
Classifier: License :: OSI Approved :: MIT License
Classifier: Natural Language :: English
Classifier: Programming Language :: Python :: 2
Classifier: Programming Language :: Python :: 2.6
Classifier: Programming Language :: Python :: 2.7
Classifier: Programming Language :: Python :: 3
Classifier: Programming Language :: Python :: 3.3
Classifier: Programming Language :: Python :: 3.4
